pdf_merger_cli/__init__.py
pdf_merger_cli/__main__.py
pdf_merger_cli-1.1.0.dist-info/licenses/LICENSE
pdf_merger_cli-1.1.0.dist-info/METADATA
pdf_merger_cli-1.1.0.dist-info/WHEEL
pdf_merger_cli-1.1.0.dist-info/entry_points.txt
pdf_merger_cli-1.1.0.dist-info/top_level.txt
pdf_merger_cli-1.1.0.dist-info/RECORD
