Metadata-Version: 2.4
Name: pdf-merger-cli
Version: 1.1.0
Summary: CLI tool to merge PDF files
Author: Francesco Dell'Ascenza
Requires-Python: >=3.8
License-File: LICENSE
Requires-Dist: typer[all]
Requires-Dist: PyPDF2
Dynamic: license-file
